{"spvCodesFilePath": "./cache/SPV/0dd5ab060cee6174f79222d0a46fb19d_codes.spv", "uniformsDesc": {"UniformsMaterial": {"binding": 2, "location": 0, "set": 0, "type": 2}, "UniformsModel": {"binding": 0, "location": 0, "set": 0, "type": 2}, "UniformsScene": {"binding": 1, "location": 0, "set": 0, "type": 2}, "u_albedoMap": {"binding": 3, "location": 0, "set": 0, "type": 1}, "u_aoMap": {"binding": 6, "location": 0, "set": 0, "type": 1}, "u_irradianceMap": {"binding": 8, "location": 0, "set": 0, "type": 1}, "u_metalRoughnessMap": {"binding": 7, "location": 0, "set": 0, "type": 1}, "u_normalMap": {"binding": 4, "location": 0, "set": 0, "type": 1}, "u_prefilterMap": {"binding": 9, "location": 0, "set": 0, "type": 1}}}